bluebox_users_client/__init__.py
bluebox_users_client/errors.py
bluebox_users_client/users/__init__.py
bluebox_users_client/users/data_mappers.py
bluebox_users_client/users/entities.py
bluebox_users_client/users/errors.py
bluebox_users_client/users/proto/__init__.py
bluebox_users_client/users/proto/users_objects_pb2.py
bluebox_users_client/users/proto/users_objects_pb2_grpc.py
bluebox_users_client/users/proto/users_services_pb2.py
bluebox_users_client/users/proto/users_services_pb2_grpc.py
bluebox_users_client/users/services.py
bluebox_users_client-0.1.0.dev1.dist-info/METADATA
bluebox_users_client-0.1.0.dev1.dist-info/WHEEL
bluebox_users_client-0.1.0.dev1.dist-info/RECORD
